fusor/__init__.py
fusor/config.py
fusor/exceptions.py
fusor/fusion_caller_models.py
fusor/fusion_matching.py
fusor/fusor.py
fusor/harvester.py
fusor/models.py
fusor/nomenclature.py
fusor/tools.py
fusor/translator.py
fusor/examples/README.md
fusor/examples/__init__.py
fusor/examples/alk.json
fusor/examples/bcr_abl1.json
fusor/examples/bcr_abl1_expanded.json
fusor/examples/ewsr1.json
fusor/examples/ewsr1_elements_only.json
fusor/examples/ewsr1_no_assay.json
fusor/examples/ewsr1_no_causative_event.json
fusor/examples/igh_myc.json
fusor/examples/tpm3_itd.json
fusor/examples/tpm3_ntrk1.json
fusor/examples/tpm3_pdgfrb.json
fusor-0.9.2.dist-info/licenses/LICENSE
fusor-0.9.2.dist-info/METADATA
fusor-0.9.2.dist-info/WHEEL
fusor-0.9.2.dist-info/top_level.txt
fusor-0.9.2.dist-info/RECORD
