Metadata-Version: 2.4
Name: fusor
Version: 0.9.2
Summary: Computable object representation and validation for gene fusions
Author-email: Alex Wagner <alex.wagner@nationwidechildrens.org>, Kori Kuzma <kori.kuzma@nationwidechildrens.org>, James Stevenson <james.stevenson@nationwidechildrens.org>, Katie Stahl <kathryn.stahl@nationwidechildrens.org>, Jeremy Arbesfeld <jeremy.arbesfeld@nationwidechildrens.org>
License: 
Project-URL: Homepage, https://github.com/cancervariants/fusor
Project-URL: Documentation, https://github.com/cancervariants/fusor
Project-URL: Changelog, https://github.com/cancervariants/fusor/releases
Project-URL: Source, https://github.com/cancervariants/fusor
Project-URL: Bug Tracker, https://github.com/cancervariants/fusor/issues
Classifier: Development Status :: 3 - Alpha
Classifier: Framework :: Pydantic
Classifier: Framework :: Pydantic :: 2
Classifier: Intended Audience :: Science/Research
Classifier: Intended Audience :: Developers
Classifier: Topic :: Scientific/Engineering :: Bio-Informatics
Classifier: License :: OSI Approved :: MIT License
Classifier: Programming Language :: Python :: 3
Classifier: Programming Language :: Python :: 3.11
Classifier: Programming Language :: Python :: 3.12
Classifier: Programming Language :: Python :: 3.13
Requires-Python: >=3.11
License-File: LICENSE
Requires-Dist: pydantic==2.*
Requires-Dist: ga4gh.vrs<3.0,>=2.1.4
Requires-Dist: biocommons.seqrepo
Requires-Dist: gene-normalizer~=0.10.0
Requires-Dist: civicpy~=5.0
Requires-Dist: cool-seq-tool~=0.15.0
Provides-Extra: tests
Requires-Dist: pytest; extra == "tests"
Requires-Dist: pytest-cov; extra == "tests"
Requires-Dist: pytest-asyncio; extra == "tests"
Provides-Extra: dev
Requires-Dist: pre-commit>=4.2.0; extra == "dev"
Requires-Dist: ruff==0.12.1; extra == "dev"
Provides-Extra: docs
Requires-Dist: sphinx<8.2.0,>=7.2; extra == "docs"
Requires-Dist: sphinx-autodoc-typehints==1.22.0; extra == "docs"
Requires-Dist: sphinx-autobuild==2021.3.14; extra == "docs"
Requires-Dist: sphinx-copybutton==0.5.2; extra == "docs"
Requires-Dist: sphinxext-opengraph==0.8.2; extra == "docs"
Requires-Dist: furo>=2023.9.10; extra == "docs"
Requires-Dist: sphinx-github-changelog==1.2.1; extra == "docs"
Dynamic: license-file
